ensae_teaching_cs/__init__.py
ensae_teaching_cs/__main__.py
ensae_teaching_cs/pandas_helper.py
ensae_teaching_cs/rss_teachings.xml
ensae_teaching_cs/automation/R_install.r
ensae_teaching_cs/automation/__init__.py
ensae_teaching_cs/automation/ftp_publish_helper.py
ensae_teaching_cs/automation/jenkins_helper.py
ensae_teaching_cs/automation/module_backup.py
ensae_teaching_cs/automation/modules_documentation.py
ensae_teaching_cs/automation/notebook_test_helper.py
ensae_teaching_cs/automation/rss_teachings_blog.py
ensae_teaching_cs/automation/teaching_modules.py
ensae_teaching_cs/automation/win_setup_helper.py
ensae_teaching_cs/automation_students/__init__.py
ensae_teaching_cs/automation_students/git_helper.py
ensae_teaching_cs/automation_students/interro_motif.py
ensae_teaching_cs/automation_students/mail_helper.py
ensae_teaching_cs/automation_students/projects_helper.py
ensae_teaching_cs/automation_students/projects_repository.py
ensae_teaching_cs/automation_students/quick_tasks.py
ensae_teaching_cs/automation_students/repository_exception.py
ensae_teaching_cs/automation_students/send_feedback.py
ensae_teaching_cs/cli/__init__.py
ensae_teaching_cs/cli/code.py
ensae_teaching_cs/data/__init__.py
ensae_teaching_cs/data/crypt_helper.py
ensae_teaching_cs/data/data1a.py
ensae_teaching_cs/data/data2a.py
ensae_teaching_cs/data/data_helper.py
ensae_teaching_cs/data/data_irep.py
ensae_teaching_cs/data/data_shape_files.py
ensae_teaching_cs/data/data_ts.py
ensae_teaching_cs/data/datacpt.py
ensae_teaching_cs/data/datasql.py
ensae_teaching_cs/data/datatext.py
ensae_teaching_cs/data/dataweb.py
ensae_teaching_cs/data/datazips.py
ensae_teaching_cs/data/gutenberg.py
ensae_teaching_cs/data/imagenet_classes.py
ensae_teaching_cs/data/data_1a/__init__.py
ensae_teaching_cs/data/data_1a/donnees_enquete_2003_television.txt
ensae_teaching_cs/data/data_1a/marathon.txt
ensae_teaching_cs/data/data_2a/__init__.py
ensae_teaching_cs/data/data_2a/wines-quality.csv
ensae_teaching_cs-0.10.3120.dist-info/LICENSE.txt
ensae_teaching_cs-0.10.3120.dist-info/METADATA
ensae_teaching_cs-0.10.3120.dist-info/WHEEL
ensae_teaching_cs-0.10.3120.dist-info/top_level.txt
ensae_teaching_cs-0.10.3120.dist-info/RECORD
