Metadata-Version: 2.1
Name: ensae-teaching-cs
Version: 0.10.3120
Summary: Materials for teachings, notebooks, helpers...
Home-page: http://www.xavierdupre.fr/app/ensae_teaching_cs/helpsphinx/index.html
Author: Xavier Dupré
Author-email: xavier.dupre@gmail.com
License: MIT
Download-URL: https://github.com/sdpython/ensae_teaching_cs/
Keywords: ensae_teaching_cs,ENSAE,sqllite,database,teachings
Platform: UNKNOWN
Classifier: Programming Language :: Python :: 3
Classifier: Intended Audience :: Developers
Classifier: Topic :: Scientific/Engineering
Classifier: Topic :: Education
Classifier: License :: OSI Approved :: MIT License
Classifier: Development Status :: 5 - Production/Stable
Requires-Dist: pyquickhelper (>=1.9.3280)
Requires-Dist: pyensae (>=1.2.788)
Requires-Dist: pymyinstall
Requires-Dist: pymmails (>=0.3)
Requires-Dist: scikit-learn (>=0.22)
Requires-Dist: pyrsslocal
Requires-Dist: pandas (>=1.0)
Requires-Dist: numpy
Requires-Dist: pyenbc
Requires-Dist: matplotlib
Requires-Dist: jupyter
Requires-Dist: mlstatpy
Requires-Dist: manydataapi
Requires-Dist: mlinsights (>=0.2.360)
